setuppanel/__init__.py
setuppanel/setuppanel.py
SetupPanel-1.0.3.dist-info/METADATA
SetupPanel-1.0.3.dist-info/WHEEL
SetupPanel-1.0.3.dist-info/top_level.txt
SetupPanel-1.0.3.dist-info/RECORD
