Metadata-Version: 2.1
Name: SetupPanel
Version: 1.0.3
Summary: Intuitive and flexible configuration of interactive embed-based setup panels for discord.py
Home-page: https://gitlab.com/marwynnsomridhivej/setuppanel
Author: Marwynn Somridhivej
License: MIT
Platform: UNKNOWN
Classifier: License :: OSI Approved :: MIT License
Classifier: Development Status :: 4 - Beta
Classifier: Intended Audience :: Developers
Classifier: Natural Language :: English
Classifier: Programming Language :: Python :: 3.6
Classifier: Programming Language :: Python :: 3.7
Classifier: Programming Language :: Python :: 3.8
Classifier: Programming Language :: Python :: 3.9
Provides-Extra: dpy
Requires-Dist: discord.py ; extra == 'dpy'
Provides-Extra: dpyv
Requires-Dist: discord.py[voice] ; extra == 'dpyv'
